ladybug_pandas/__init__.py
ladybug_pandas/dataframe.py
ladybug_pandas/series.py
ladybug_pandas/accessors/__init__.py
ladybug_pandas/accessors/ladybug.py
ladybug_pandas/accessors/psychrometrics.py
ladybug_pandas/extension_types/__init__.py
ladybug_pandas/extension_types/arraytype.py
ladybug_pandas/extension_types/dtype.py
ladybug_pandas-0.4.1.dist-info/LICENSE
ladybug_pandas-0.4.1.dist-info/METADATA
ladybug_pandas-0.4.1.dist-info/WHEEL
ladybug_pandas-0.4.1.dist-info/top_level.txt
ladybug_pandas-0.4.1.dist-info/RECORD
