Metadata-Version: 2.1
Name: ladybug-pandas
Version: 0.4.1
Summary: A ladybug extension powered by pandas
Home-page: https://github.com/ladybug-tools/ladybug-pandas
Author: Ladybug Tools
Author-email: info@ladybug.tools
License: AGPL-3.0
Platform: UNKNOWN
Classifier: Programming Language :: Python :: 3.6
Classifier: Programming Language :: Python :: Implementation :: CPython
Classifier: License :: OSI Approved :: GNU Affero General Public License v3
Classifier: Operating System :: OS Independent
Requires-Dist: pandas (>=1.1.4)
Requires-Dist: scipy (>=1.5.4)
Requires-Dist: ladybug-core (>=0.39.23)
Provides-Extra: arrow
Requires-Dist: pyarrow ; extra == 'arrow'
